PyGraphicUI/Animations.py
PyGraphicUI/Attributes.py
PyGraphicUI/Functions.py
PyGraphicUI/PyCharts.py
PyGraphicUI/PyObjects.py
PyGraphicUI/PyStyleSheets.py
PyGraphicUI/__init__.py
PyGraphicUI/Charts/Canvas.py
PyGraphicUI/Charts/__init__.py
PyGraphicUI/Charts/Financial/BaseChart.py
PyGraphicUI/Charts/Financial/__init__.py
PyGraphicUI/Objects/AbstractTableModel.py
PyGraphicUI/Objects/Calendar.py
PyGraphicUI/Objects/ComboBox.py
PyGraphicUI/Objects/Dialogs.py
PyGraphicUI/Objects/DoubleSpinBox.py
PyGraphicUI/Objects/HeaderView.py
PyGraphicUI/Objects/Label.py
PyGraphicUI/Objects/Layouts.py
PyGraphicUI/Objects/LineEdit.py
PyGraphicUI/Objects/MainWindow.py
PyGraphicUI/Objects/PadChoicers.py
PyGraphicUI/Objects/ProgressBars.py
PyGraphicUI/Objects/PushButton.py
PyGraphicUI/Objects/ScrollAreas.py
PyGraphicUI/Objects/SortFilterProxyModel.py
PyGraphicUI/Objects/SpinBox.py
PyGraphicUI/Objects/StackedWidget.py
PyGraphicUI/Objects/TableView.py
PyGraphicUI/Objects/TextEdit.py
PyGraphicUI/Objects/Watches.py
PyGraphicUI/Objects/Widgets.py
PyGraphicUI/Objects/__init__.py
PyGraphicUI/StyleSheets/__init__.py
PyGraphicUI/StyleSheets/Objects/AbstractButton.py
PyGraphicUI/StyleSheets/Objects/AbstractItemView.py
PyGraphicUI/StyleSheets/Objects/Base.py
PyGraphicUI/StyleSheets/Objects/Calendar.py
PyGraphicUI/StyleSheets/Objects/ComboBox.py
PyGraphicUI/StyleSheets/Objects/Dialog.py
PyGraphicUI/StyleSheets/Objects/DoubleSpinBox.py
PyGraphicUI/StyleSheets/Objects/HeaderView.py
PyGraphicUI/StyleSheets/Objects/Label.py
PyGraphicUI/StyleSheets/Objects/LineEdit.py
PyGraphicUI/StyleSheets/Objects/ListView.py
PyGraphicUI/StyleSheets/Objects/ProgressBar.py
PyGraphicUI/StyleSheets/Objects/PushButton.py
PyGraphicUI/StyleSheets/Objects/ScrollArea.py
PyGraphicUI/StyleSheets/Objects/ScrollBar.py
PyGraphicUI/StyleSheets/Objects/SpinBox.py
PyGraphicUI/StyleSheets/Objects/StackedWidget.py
PyGraphicUI/StyleSheets/Objects/TableCornerButton.py
PyGraphicUI/StyleSheets/Objects/TableView.py
pygraphicui-1.5.9.dist-info/METADATA
pygraphicui-1.5.9.dist-info/WHEEL
pygraphicui-1.5.9.dist-info/top_level.txt
pygraphicui-1.5.9.dist-info/RECORD
