Metadata-Version: 2.4
Name: PyGraphicUI
Version: 1.5.9
Summary: PyGraphicUI enhances PyQt6 GUI development with simplified widget creation, intuitive layout management, dynamic time-based widgets, and an object-oriented approach to stylesheets, reducing boilerplate and improving code readability.
Author: oddshellnick
Author-email: oddshellnick.programming@gmail.com
Requires-Dist: setuptools>=75.1.0
Requires-Dist: matplotlib>=3.10.0
Requires-Dist: mplfinance>=0.12.10b0
Requires-Dist: pandas>=2.2.3
Requires-Dist: pyqt6>=6.8.0
Requires-Dist: pyqt6-sip>=13.9.1
Requires-Dist: python-dateutil>=2.9.0.post0
Requires-Dist: codeimprover>=1.1.8
Dynamic: author
Dynamic: author-email
Dynamic: description
Dynamic: description-content-type
Dynamic: requires-dist
Dynamic: summary
